{"componentChunkName":"component---src-templates-index-tsx","path":"/page/2","result":{"data":{"allGithubRepository":{"edges":[{"node":{"name":"com.ceco.q.gravitybox","description":"GravityBox [Q]","url":"https://github.com/Xposed-Modules-Repo/com.ceco.q.gravitybox","homepageUrl":"https://forum.xda-developers.com/showthread.php?t=3974497","collaborators":{"edges":[{"node":{"login":"C3C0","name":null}}]},"readme":"# GravityBox [Q]\n\n**GravityBox** is a module which primary goal is to provide the users of devices running vanilla or close to vanilla Android\n\nwith a tweak box that turns their stock ROM into a custom ROM packed with additional features and tweaks;\n\nwithout the need of flashing a custom ROM. Most of the preferences can be changed on-the-fly without rebooting.\n\n## !!!!!! WARNING !!!!!!\nThis module utilizes EdXposed Framework which is still in early development stage and may contain bugs or might not be fully compatible with system of your Android device. I take no responsibility for any issues arising from using GravityBox with EdXposed and strongly recommend creating a full backup of your device before activating the module.\n\n***THIS VERSION IS FOR ANDROID 10 (Q) ROMs***\n- For Lollipop, use GravityBox [LP]\n- For KitKat, use GravityBox [KK]\n- For JellyBean, use GravityBox [JB]\n- For Marshmallow, use GravityBox [MM]\n- For Nougat, use GravityBox [N]\n- For Oreo, use GravityBox [O]\n- For Pie, use GravityBox [P]\n\n## Main features\n- QuickSettings tile management with additional tiles\n- Pie Controls\n- Expanded desktop with semi-immersive and immersive modes\n- Lockscreen tweaks\n- Statusbar tweaks\n- Navigation bar tweaks\n- Power tweaks\n- Display tweaks\n- Media tweaks\n- Phone tweaks\n- Hardware key actions\n- Launcher tweaks\n- Screen recording\n- Smart radio\n- Notification control (per-app notification LED/sounds/vibrations)\n- Fingerprint Launcher\n- Advanced tuning of Framework and System UI parameters\n- Media Visualizer\n\n... and many more\n\n## Compatibility\n- Supports AOSP devices running vanilla Android 10\n- Supports OnePlus devices running official OxygenOS\n- Supports Pixel devices running official Google OS\n- *DOES NOT* support devices running ROMs vastly modified by device manufacturers (HTC Sense, LG, Samsung Touchwiz, MIUI, LeWa, Xperia, ...)\n- *SHOULD NOT* be used with custom ROMs like Lineage, AOSPA, or any other derivative - it makes no sense since the most of the features are already in the ROM (may cause conflicts and unexpected behavior)\n\n## Requirements\n- Magisk v20 or later\n- Riru core v21 or later (Magisk module)\n- Riru - EdXposed v0.4 or later (Magisk module; YAHFA or Sandhook whatever works best on your device)\n- EdXposed Manager\n\n## Info about premium features and PayPal transaction ID verification system\n1. Those who supported development via PayPal donation can use their PayPal transaction ID to unlock premium features. Currently there are two premium features: 1) Backup/restore of GB settings 2) Ultimate notification control\n\n2. If you contributed to the project by providing translations, code fragments, or by any other way. You can apply for a free transaction ID by contacting me via PM @ forum.xda-developers.com\n\n3. Be aware that there's a system that can identify potential transaction ID abuse. E.g. when one ID is being used by more users. Such IDs will get blocked automatically. This can also happen when you previously exposed your ID in public forum and other users took advantage of it. If this is the case, contact me via PM so I can issue new, special ID. In case you own more devices, you can use one transaction ID on up to 10 of them.\n\n4. If you are using your own custom builds of GB for personal use, you will get hash mismatch upon verifying your ID as verification system accepts requests only from official releases of GB. If you want to be able to verify IDs with your custom build, contact me via PM so I can setup a special hash for your build. If you are using a custom build that you provide for broader group of users (e.g. in a custom ROM), It is necessary to ask for new hash everytime your new custom version is released for public use. These rules are based on mutual trust so please, do not violate them.\n","summary":"All-in-one complex module for devices running vanilla Android 10 (Q)","sourceUrl":"https://github.com/GravityBox/GravityBox/tree/q","hide":false,"additionalAuthors":[],"childGitHubReadme":{"childMarkdownRemark":{"excerpt":"GravityBox [Q] GravityBox is a module which primary goal is to provide the users of devices running vanilla or close to vanilla Android with a tweak box that turns their stock ROM into a custom ROM packed with additional features and tweaks; without…"}}}},{"node":{"name":"io.github.tehcneko.mifit","description":"MiFit/小米运动 Hook","url":"https://github.com/Xposed-Modules-Repo/io.github.tehcneko.mifit","homepageUrl":"","collaborators":{"edges":[]},"readme":"# MiFit Hook\nLet MiFit treat Nekogram and Catogram as Telegram.\n","summary":"Let MiFit treat Nekogram and Catogram as Telegram.\n去除广告，以及让小米运动将 Nekogram 与 Catogram 视为 Telegram。","sourceUrl":null,"hide":false,"additionalAuthors":null,"childGitHubReadme":{"childMarkdownRemark":{"excerpt":"MiFit Hook Let MiFit treat Nekogram and Catogram as Telegram."}}}},{"node":{"name":"com.chacha.notigif","description":"Notigif","url":"https://github.com/Xposed-Modules-Repo/com.chacha.notigif","homepageUrl":"https://forum.xda-developers.com/t/xposed-notigif-add-a-gif-to-notifications-panel.4165259/","collaborators":{"edges":[{"node":{"login":"Jck0day","name":"Charly"}}]},"readme":"## **This module allow you to add a gif or a picutre of your choice in notifications panel !**\n/!\\SINCE RIRU V22 YOU MUST ENABLE RESOURCE HOOK IN EDXPOSED SETTINGS/!\\\n\n/!\\ SystemUI must be restart to apply modifications /!\\\nOfficially working with :\nOneUI (1.0 & 2.x)\nAOSP (N to R)\nOxygenOS\nMIUI\n\n/*PS : Don't hesitate to try it on your rom and tell me if it work or no, I can support a lot of roms with your help*/\n\n## Used libraries (Big thanks to all there developpers) :\n[Fileprefs](https://github.com/chengxuncc/fileprefs)\n\n[XposedBridge](https://github.com/rovo89/XposedBridge)\n\n[Libsuperuser](https://github.com/Chainfire/libsuperuser)\n\n[Glide](https://github.com/bumptech/glide)\n\nContact :\nIf you want to help me or suggest me some ideas you can send mail\n\nMail : jck0day@gmail.com\n\nMy other module :\n\n[Samsung Music Customiser](https://forum.xda-developers.com/t/xposed-lsposed-samsung-music-customiser-change-app-colors.4076893/)\n\n[Samsung Messages Customiser](https://forum.xda-developers.com/t/xposed-lsposed-samsung-messages-customiser-change-app-colors.4104635/)\n\n## You can give me [donation](https://www.paypal.com/cgi-bin/webscr?cmd=_s-xclick&hosted_button_id=A3YW496LXQZ5A&source=url) if you want to support all my free works. A big thanks if you give me this reward it's very sympathic :)\n\nThank you for reading this, don't forget to press thanks on my XDA page ^_^\nPS : I'm french, so I try to speak english I hope your eyes still lives and that there are not too mistakes.\n","summary":"Allow you to add a gif or a picture in your notifications panel !","sourceUrl":null,"hide":false,"additionalAuthors":null,"childGitHubReadme":{"childMarkdownRemark":{"excerpt":"This module allow you to add a gif or a picutre of your choice in notifications panel ! /!\\SINCE RIRU V22 YOU MUST ENABLE RESOURCE HOOK IN EDXPOSED SETTINGS/!\\ /!\\ SystemUI must be restart to apply modifications /! Officially working with :\nOneUI (1…"}}}},{"node":{"name":"com.test.unlockmiui","description":"解锁MIUI+","url":"https://github.com/Xposed-Modules-Repo/com.test.unlockmiui","homepageUrl":"https://github.com/zhang0281/UnlockMiui","collaborators":{"edges":[{"node":{"login":"zhang0281","name":"zhang"}}]},"readme":"# 解锁MIUI+\n\n在未适配的型号（小米手机）上使用MIUI＋。\n\n## 模块作用\n\n去除MIUI+在扫描二维码时的机型检测。并在```设置```->```连接和共享```中显示```MIUI+ Beta版```设置项。\n\n## 模块需求\n\n1. MIUI12.5\n2. Android 11\n\n## 安装方式\n\n1. 在下方的链接中下载新版本的MIUI+相关安装包并安装。\n![需求文件](/picture/需求文件.jpg)\n2. 安装模块并启用，选中```MIUI+ Beta版```和```设置(com.android.settings)```。\n3. 强制停止```MIUI+```和```设置```。\n\n## 提取出的MIUI+相关文件\n\n[下载链接](https://wws.lanzoux.com/b01u1if2d)密码:h61h\n\n（链接内有模块和提取出来的小米互联通信服务，扫一扫，MIUI+。）\n\n\n注：该模块只去掉了在扫描二维码时的机型检测，无法解决其他问题。如使用了该模块仍旧无法使用MIUI＋，请查看是否已经关闭小米快传或者自行百度。\n","summary":"解锁MIUI12.5的MIUI+","sourceUrl":"https://github.com/zhang0281/UnlockMiui","hide":false,"additionalAuthors":[],"childGitHubReadme":{"childMarkdownRemark":{"excerpt":"解锁MIUI+ 在未适配的型号（小米手机）上使用MIUI＋。 模块作用 去除MIUI+在扫描二维码时的机型检测。并在设置->连接和共享中显示MIUI+ Beta版设置项。 模块需求 MIUI12.5 Android 11 安装方式 在下方的链接中下载新版本的MIUI+相关安装包并安装。 需求文件\n2. 安装模块并启用，选中MIUI+ Beta版和设置(com.android.settings)。\n3. 强制停止MIUI+和设置。 提取出的MIUI+相关文件 下载链接密码:h61h （链接内有模…"}}}},{"node":{"name":"name.mikanoshi.customiuizer","description":"CustoMIUIzer","url":"https://github.com/Xposed-Modules-Repo/name.mikanoshi.customiuizer","homepageUrl":"https://forum.xda-developers.com/t/3910732/","collaborators":{"edges":[{"node":{"login":"Mikanoshi","name":null}}]},"readme":"# CustoMIUIzer\n\nCustoMIUIzer module contains a variety of mods that will provide additional functionality for your MIUI device.\n\n## System compatibility\nModule was written, tested and is mainly intended for MIUI 10-12 on Android 9-10. Mods are not guaranteed to fully work on any other versions, especially lower MIUI versions. APK installation is limited to Android 7+.\n\n## EdXposed Framework compatibility\nFramework must be 0.4.6.4 or 0.5.1.4+, versions in between won't work. Module must not be installed from Google Play if 0.4.6.4 is used with app list mode enabled.\n\n## List of mods\nAutogenerated list based on git files.\n- [English version](https://code.highspec.ru/CustoMIUIzer/)\n- [Russian version](https://code.highspec.ru/CustoMIUIzer/ru)\n- [German version](https://code.highspec.ru/CustoMIUIzer/de)\n- [Ukrainian version](https://code.highspec.ru/CustoMIUIzer/uk)\n- [Turkish version](https://code.highspec.ru/CustoMIUIzer/tr)\n- [Italian version](https://code.highspec.ru/CustoMIUIzer/it)\n- [Spanish version](https://code.highspec.ru/CustoMIUIzer/es)\n- [Chinese (Simplified) version](https://code.highspec.ru/CustoMIUIzer/zh)\n- [Portuguese (Brazil) version](https://code.highspec.ru/CustoMIUIzer/pt)\n\n## Known bugs\n- [English version](https://code.highspec.ru/Mikanoshi/CustoMIUIzer/raw/branch/master/BUGS_EN)\n- [Russian version](https://code.highspec.ru/Mikanoshi/CustoMIUIzer/raw/branch/master/BUGS_RU)\n\n## Troubleshooting\nYou can send a detailed report with a description of your problem from CustoMIUIzer itself or create new issue on [issue tracker](https://code.highspec.ru/Mikanoshi/CustoMIUIzer/issues).\n\n## Localization\n[Translate CustoMIUIzer](https://localize.highspec.ru/)\n","summary":"Customize your MIUI ROM","sourceUrl":"https://code.highspec.ru/Mikanoshi/CustoMIUIzer","hide":false,"additionalAuthors":[],"childGitHubReadme":{"childMarkdownRemark":{"excerpt":"CustoMIUIzer CustoMIUIzer module contains a variety of mods that will provide additional functionality for your MIUI device. System compatibility Module was written, tested and is mainly intended for MIUI 10-12 on Android 9-10. Mods are not guarante…"}}}},{"node":{"name":"io.github.lsposed.disableflagsecure","description":"Disable FLAG_SECURE","url":"https://github.com/Xposed-Modules-Repo/io.github.lsposed.disableflagsecure","homepageUrl":"","collaborators":{"edges":[]},"readme":"# DisableFlagSecure\nDisable FLAG_SECURE on all windows, enabling screenshots in apps that normally wouldn\\'t allow it.","summary":"Disable FLAG_SECURE on all windows, enabling screenshots in apps that normally wouldn't allow it.","sourceUrl":"https://github.com/LSPosed/DisableFlagSecure","hide":false,"additionalAuthors":null,"childGitHubReadme":{"childMarkdownRemark":{"excerpt":"DisableFlagSecure Disable FLAG_SECURE on all windows, enabling screenshots in apps that normally wouldn't allow it."}}}},{"node":{"name":"com.varuns2002.disable_flag_secure","description":"Disable-FLAG_SECURE","url":"https://github.com/Xposed-Modules-Repo/com.varuns2002.disable_flag_secure","homepageUrl":"","collaborators":{"edges":[{"node":{"login":"VarunS2002","name":"Varun Shanbhag"}}]},"readme":"# Disable-FLAG_SECURE\n\nXposed Module to Disable `FLAG_SECURE`, enabling screenshots, screen sharing and recording in apps that normally\nwouldn't allow it.\n\n![Download-Count](https://img.shields.io/github/downloads/Xposed-Modules-Repo/com.varuns2002.disable_flag_secure/total?color=blue)\n\n## Usage for LSPosed:\n\n- Enable the module\n- Select `System Framework`\n- Select the target app in which you want to enable screenshots\n- Reboot\n\n## Note:\n\n- This app does not prevent apps from detecting that you've taken a screenshot or recorded it like Snap or Instagram.\n  This only enables it in apps that prohibit screenshots and recording. So don't screenshot your girlfriend's nudes.\n  (You probably don't have one since you're reading this anyway)\n\n\n- Apps Tested on:\n    - Amazon Prime Video\n    - Netflix ([Read Additional Instructions](#additional-information-on-drm-encrypted-content))\n    - Disney+ ([Read Additional Instructions](#additional-information-on-drm-encrypted-content))\n    - Telegram (Secret Chat & Disappearing Media)\n    - Reddit (Anonymous Browsing Mode)\n    - Google Chrome (Incognito Mode)\n    - Brave Browser (Incognito Mode)\n\n- This module may work on other apps too with or\n  without [`liboemcrypto.so disabler`](https://github.com/Magisk-Modules-Repo/liboemcryptodisabler).\n  ([Read Additional Instructions](#additional-information-on-drm-encrypted-content))\n\n- You can contribute names of apps [here](https://github.com/VarunS2002/Xposed-Disable-FLAG_SECURE) that are working and\n  are not listed here, so I can add it to the list.\n\n- If you face any issue or have a suggestion then feel free to open an\n  issue [here](https://github.com/VarunS2002/Xposed-Disable-FLAG_SECURE).\n\n- This app is a fork of the existing apps but with better compatibility:\n    - https://github.com/veeti/DisableFlagSecure/\n    - https://github.com/LSPosed/DisableFlagSecure/\n    - https://gitlab.com/azhao12345/disableflagsecure/\n\n### Additional Information on DRM encrypted content\n\nThis is applicable only for some apps on some devices. If you aren't facing any issues, you can ignore these\ninstructions.\n\nWhen playing DRM encrypted content, most devices will use hardware decryption capabilities. This hardware decryption\nwill push the video directly onto the screen, bypassing any screenshots/screenshare/recording functionality.\n\nOne possible solution is to disable this hardware decryption by installing the Magisk\nmodule [`liboemcrypto.so disabler`](https://github.com/Magisk-Modules-Repo/liboemcryptodisabler). This will force the\ndevice to not use hardware decryption and in combination with this module will enable screenshots, screen sharing and\nrecording.\n\nInstalling this module might have unintended consequences, such as lowered video quality.\n[Read more](https://forum.xda-developers.com/t/magisk-module-liboemcrypto-disabler-for-drm-protected-content-netflix-my5-etc.3794393)\n","summary":"Xposed Module to Disable FLAG_SECURE, enabling screenshots, screen sharing and recording in apps that normally wouldn't allow it.","sourceUrl":"https://github.com/VarunS2002/Xposed-Disable-FLAG_SECURE","hide":false,"additionalAuthors":null,"childGitHubReadme":{"childMarkdownRemark":{"excerpt":"Disable-FLAG_SECURE Xposed Module to Disable FLAG_SECURE, enabling screenshots, screen sharing and recording in apps that normally\nwouldn't allow it. Download-Count Usage for LSPosed: Enable the module Select System Framework Select the target app i…"}}}},{"node":{"name":"com.chacha.smessagescustom","description":"Samsung Messages Customiser","url":"https://github.com/Xposed-Modules-Repo/com.chacha.smessagescustom","homepageUrl":"https://forum.xda-developers.com/t/xposed-lsposed-samsung-messages-customiser-change-app-colors.4104635/","collaborators":{"edges":[{"node":{"login":"Jck0day","name":"Charly"}}]},"readme":"Hey !\n# This module allow you to customize colors of Samsung Messages app !\n\n/!\\ Samsung Messages must be killed after applying new colors /!\\\n /!\\ THIS IS NOT COMPATIBLE WITH THE ONEUI 2.x MESSAGES VERSION /!\\\n\nDONT FORGET TO SAY THANKS ON MY XDA PAGE PLS '^^\n\n## Used libraries :\n[Fileprefs](https://github.com/chengxuncc/fileprefs)\n\n[PhotoshopColorPicker](https://github.com/AzeeSoft/AndroidPhotoshopColorPicker)\n\n[XposedBridge](https://github.com/rovo89/XposedBridge)\n\n[Libsuperuser](https://github.com/Chainfire/libsuperuser)\n\n[Airbnb Paris](https://github.com/airbnb/paris)\n\n\nIf you want to help me or suggest me some ideas you can send mail\nMail : jck0day@gmail.com\n\n### You can now give me [donation](https://www.paypal.com/cgi-bin/webscr?cmd=_s-xclick&hosted_button_id=A3YW496LXQZ5A&source=url) if you want to support all my free works. A big thanks if you give me this reward it's very sympathic :)\n","summary":"This module allow you to customise colors of Samsung Messages app !\n /!\\ THIS IS NOT COMPATIBLE WITH THE ONEUI 2.x MESSAGES VERSION /!\\","sourceUrl":null,"hide":false,"additionalAuthors":null,"childGitHubReadme":{"childMarkdownRemark":{"excerpt":"Hey ! This module allow you to customize colors of Samsung Messages app ! /!\\ Samsung Messages must be killed after applying new colors /! /!\\ THIS IS NOT COMPATIBLE WITH THE ONEUI 2.x MESSAGES VERSION /!\\ DONT FORGET TO SAY THANKS ON MY XDA PAGE PL…"}}}},{"node":{"name":"cn.dreamn.qianji_auto","description":"钱迹自动记账","url":"https://github.com/Xposed-Modules-Repo/cn.dreamn.qianji_auto","homepageUrl":"","collaborators":{"edges":[{"node":{"login":"dreamncn","name":"Dreamn"}}]},"readme":"# 钱迹自动记账插件\n\n![](https://img.shields.io/github/issues/dreamncn/Qianji_auto)\n![](https://img.shields.io/badge/PoweredBy-Dreamn-f39f37)\n![](https://img.shields.io/github/license/dreamncn/VPay)\n![](https://img.shields.io/github/stars/dreamncn/Qianji_auto.svg?label=Stars&style=social)\n\n\n## 项目简介&功能特性\n\n> 基于钱迹自动记账接口开发的自动记账工具，具有Xposed与无障碍两种模式。\n\n框架适配：\n\n『太极』『Xposed』『EdXposed』『LSPosed』\n\n记账App已支持：\n\n『支付宝』『微信』『短信』\n\n## 贡献代码\n\n- Fork该项目到您的Github账号中\n- Clone您fork的项目到本地\n- 本地调试修改好后提交到您的项目中\n- 从您fork的项目向我的项目发起Pull Request\n\n## 部署步骤\n\n- 下载源代码到本地\n- 使用AS打开\n- Build\n\n## 下载\n\n[【酷安】自动记账](https://www.coolapk.com/apk/cn.dreamn.qianji_auto)\n\n友情提醒：自动记账仅在酷安与太极仓库发布更新，其他渠道下载注意安全。\n\n## 版本内容更新\n\n[请查看更新日志](/ChangeLog.md) \n\n## 鸣谢\n\n- [钱迹](http://www.qianjiapp.com/)\n- [XUI](https://github.com/xuexiangjys/XUI)\n\n\n## 版权声明\n\n自动记账遵循 [GPL-3.0 License](/LICENSE) 开源协议发布，并提供免费使用，请勿用于非法用途。\n\nCopyright © 2021 by dreamn (https://dreamn.cn)\n\nAll rights reserved.\n","summary":null,"sourceUrl":null,"hide":false,"additionalAuthors":null,"childGitHubReadme":{"childMarkdownRemark":{"excerpt":"钱迹自动记账插件 \n\n\n 项目简介&功能特性 基于钱迹自动记账接口开发的自动记账工具，具有Xposed与无障碍两种模式。 框架适配： 『太极』『Xposed』『EdXposed』『LSPosed』 记账App已支持： 『支付宝』『微信』『短信』 贡献代码 Fork该项目到您的Github账号中 Clone您fork的项目到本地 本地调试修改好后提交到您的项目中 从您fork的项目向我的项目发起Pull Request 部署步骤 下载源代码到本地 使用AS打开 Build 下载 【酷安】自动记账…"}}}},{"node":{"name":"com.ketal.bcrfullscreen","description":"BCR/PCR强制全屏(BCRfullscreen)","url":"https://github.com/Xposed-Modules-Repo/com.ketal.bcrfullscreen","homepageUrl":"https://github.com/KitsunePie/BCRfullscreen","collaborators":{"edges":[{"node":{"login":"keta1","name":"Ketal"}},{"node":{"login":"KyuubiRan","name":"Kitsune"}}]},"readme":"# BCRfullscreen\n让BCR/PCR最新版全屏显示\n\n## [下载](https://github.com/KitsunePie/BCRfullscreen/releases/)\n\n>[![APK: v1.3](https://img.shields.io/badge/APK-v1.3-brightgreen)](https://github.com/KitsunePie/BCRfullscreen/releases/download/1.3/app-release.apk)\n![Download-Count](https://img.shields.io/github/downloads/KitsunePie/BCRfullscreen/total?color=blue)\n\n## 支持设备:\n安卓p(9.0)以上\n\n## 使用:\n- LSPosed:\n  - 启用模块\n  - 选择 `系统框架`\n  - 重启手机\n","summary":"让BCR/PCR最新版全屏显示","sourceUrl":"https://github.com/KitsunePie/BCRfullscreen","hide":false,"additionalAuthors":null,"childGitHubReadme":{"childMarkdownRemark":{"excerpt":"BCRfullscreen 让BCR/PCR最新版全屏显示 下载 APK: v1.3 Download-Count 支持设备: 安卓p(9.0)以上 使用: LSPosed: 启用模块 选择 系统框架 重启手机"}}}},{"node":{"name":"com.coderstory.toolkit","description":"核心破解","url":"https://github.com/Xposed-Modules-Repo/com.coderstory.toolkit","homepageUrl":"","collaborators":{"edges":[{"node":{"login":"coderstory","name":"CoderStory"}}]},"readme":"# CorePatch\n\n```\nDisable signature verification For Android\n禁用安装apk时候执行的签名校验\nThe current version support android 10-11\n当前版本只支持安卓10-11\n```\n\n\n## Fetures 功能\n```\n allow downgrade application [INSTALL_FAILED_VERSION_DOWNGRADE]\n 允许降级安装应用\n\n allows direct install apps after modify file in apk [ignore invalid digest error etc..]\n 允许安装签名错误的apk\n\n allow overlay install apps with inconsistent signatures\n 允许在使用不同签名的情况下覆盖安装\n```\n\n","summary":"Disable signature verification\n版本降级,签名不一致,签名错误的apk都能安装","sourceUrl":"https://github.com/coderstory/CorePatch","hide":false,"additionalAuthors":[{"name":"coderstory","link":"https://github.com/coderstory","type":"add"}],"childGitHubReadme":{"childMarkdownRemark":{"excerpt":"CorePatch Fetures 功能"}}}},{"node":{"name":"com.alex193a.xdowngrader","description":"XDowngrader","url":"https://github.com/Xposed-Modules-Repo/com.alex193a.xdowngrader","homepageUrl":"https://twitter.com/alex193a","collaborators":{"edges":[{"node":{"login":"alex193a","name":"Alessandro Paluzzi"}}]},"readme":"# XDowngrader\n\nXDowngrader downgrades any app by allowing you to install the APK of an old version on top of the new version on Android 5 and newer.\n\nNo configuration needed*, install and restart the phone.\n\n*Make sure you allow the module to hook the **System Framework** if you are using LSPosed or EdXposed in WhiteList mode!","summary":"Allows you to downgrade any app on Android 5 and newer.","sourceUrl":"","hide":false,"additionalAuthors":[],"childGitHubReadme":{"childMarkdownRemark":{"excerpt":"XDowngrader XDowngrader downgrades any app by allowing you to install the APK of an old version on top of the new version on Android 5 and newer. No configuration needed*, install and restart the phone. *Make sure you allow the module to hook the Sy…"}}}},{"node":{"name":"com.hiwechart.translate","description":"微信学英语wechat","url":"https://github.com/Xposed-Modules-Repo/com.hiwechart.translate","homepageUrl":"","collaborators":{"edges":[{"node":{"login":"231599447","name":"cookcell"}}]},"readme":"# 微信学英语\n\n微信学英语app是一款基于XPosed模块的应用小程序，可以快速将微信中的对话转变成英文，让你一边聊天一边学习日常用语。\n\n\nQQ群:168140779\n\n![微信学英语](image.png)\n","summary":null,"sourceUrl":null,"hide":false,"additionalAuthors":null,"childGitHubReadme":{"childMarkdownRemark":{"excerpt":"微信学英语 微信学英语app是一款基于XPosed模块的应用小程序，可以快速将微信中的对话转变成英文，让你一边聊天一边学习日常用语。 QQ群:168140779 微信学英语"}}}},{"node":{"name":"com.alex193a.gmdtenabler","description":"Gmail Dark Theme Enabler ","url":"https://github.com/Xposed-Modules-Repo/com.alex193a.gmdtenabler","homepageUrl":"https://twitter.com/alex193a","collaborators":{"edges":[{"node":{"login":"alex193a","name":"Alessandro Paluzzi"}}]},"readme":"# Gmail Dark Theme Enabler\n\nAllow to use the official dark theme in Gmail on Android 9 and earlier.\n\nNo configuration needed, install and restart the phone.\n\n# Compatible versions:\n\n* 2019.08.18.267044774.release\n* 2019.09.01.268168002.release\n* 2019.09.15.270135155.release\n* 2019.10.20.278647676.release\n* 2019.11.03.280318276.release\n* 2019.11.21.283644823.release\n* 2019.12.30.289507923.release\n* 2020.01.27.293735221.release\n* 2020.02.02.294309273.release\n* 2020.02.16.297705979.release\n* 2020.03.01.300483594.release\n* 2020.03.01.300951155.release\n* 2020.03.15.302138189.release\n* 2020.03.29.306383213.release\n* 2020.03.29.306383213.Release\n* 2020.04.12.307915656.Release (universal)\n* 2020.04.12.307915656.release (noarch)\n* 2020.04.26.310266462.release (noarch)\n* 2020.04.26.310266462.Release (arm64-v8a)\n* 2020.05.17.313130477.release (noarch)\n* 2020.05.17.313130477.Release (arm64-v8a + arm-v7a)\n* 2020.05.31.316831277.release (noarch)\n* 2020.05.31.316831277.Release (arm64-v8a)\n* 2020.06.14.318184621.Release (universal)\n* 2020.06.28.320626991.Release (universal)\n* [2020.07.12.322040623.Release (universal)](https://www.apkmirror.com/apk/google-inc/gmail/gmail-2020-07-12-322040623-release-release/gmail-2020-07-12-322040623-release-android-apk-download/)\n* [2020.07.12.323583380.Release (universal)](https://www.apkmirror.com/apk/google-inc/gmail/gmail-2020-07-12-323583380-release-release/gmail-2020-07-12-323583380-release-android-apk-download/)\n* [2020.10.04.337159408.Release (universal)](https://www.apkmirror.com/apk/google-inc/gmail/gmail-2020-10-04-337159408-release-release/gmail-2020-10-04-337159408-release-2-android-apk-download/)\n* [2020.10.18.339546910.Release (universal)](https://www.apkmirror.com/apk/google-inc/gmail/gmail-2020-10-18-339546910-release-release/gmail-2020-10-18-339546910-release-2-android-apk-download/)\n* [2020.10.18.341076532.Release (universal)](https://www.apkmirror.com/apk/google-inc/gmail/gmail-2020-10-18-341076532-release-release/gmail-2020-10-18-341076532-release-2-android-apk-download/)\n* [2020.11.01.341658534.Release (universal)](https://www.apkmirror.com/apk/google-inc/gmail/gmail-2020-11-01-341658534-release-release/gmail-2020-11-01-341658534-release-2-android-apk-download/)\n* [2020.11.01.342354497.Release (universal)](https://www.apkmirror.com/apk/google-inc/gmail/gmail-2020-11-01-342354497-release-release/gmail-2020-11-01-342354497-release-2-android-apk-download/)\n* [2020.11.15.344277575.Release (universal)](https://www.apkmirror.com/apk/google-inc/gmail/gmail-2020-11-15-344277575-release-release/gmail-2020-11-15-344277575-release-2-android-apk-download/)\n* [2020.11.15.344132073.Release (universal)](https://www.apkmirror.com/apk/google-inc/gmail/gmail-2020-11-15-344132073-release-release/gmail-2020-11-15-344132073-release-android-apk-download/)\n* [2020.11.29.346182102.Release (universal)](https://www.apkmirror.com/apk/google-inc/gmail/gmail-2020-11-29-346182102-release-release/gmail-2020-11-29-346182102-release-2-android-apk-download/)\n* [2020.12.27.351479536.Release (universal)](https://www.apkmirror.com/apk/google-inc/gmail/gmail-2020-12-27-351479536-release-release/gmail-2020-12-27-351479536-release-android-apk-download/)\n* [2020.12.27.355085521.Release (universal)](https://www.apkmirror.com/apk/google-inc/gmail/gmail-2020-12-27-355085521-release-release/gmail-2020-12-27-355085521-release-2-android-apk-download/)\n* [2021.01.24.356386247.Release (universal)](https://www.apkmirror.com/apk/google-inc/gmail/gmail-2021-01-24-356386247-release-release/gmail-2021-01-24-356386247-release-2-android-apk-download/)\n* [2021.02.05.357775197.Release (universal)](https://www.apkmirror.com/apk/google-inc/gmail/gmail-2021-02-05-357775197-release-release/gmail-2021-02-05-357775197-release-android-apk-download/)\n* [2021.02.21.361222438.Release (universal)](https://www.apkmirror.com/apk/google-inc/gmail/gmail-2021-02-21-361222438-release-release/gmail-2021-02-21-361222438-release-2-android-apk-download/)\n* [2021.02.21.361635104.Release (universal)](https://www.apkmirror.com/apk/google-inc/gmail/gmail-2021-02-21-361635104-release-release/gmail-2021-02-21-361635104-release-android-apk-download/)\n* [2021.03.07.364486182.Release (universal)](https://www.apkmirror.com/apk/google-inc/gmail/gmail-2021-03-07-364486182-release-release/gmail-2021-03-07-364486182-release-2-android-apk-download/)\n* [2021.03.07.363560676.Release (universal)](https://www.apkmirror.com/apk/google-inc/gmail/gmail-2021-03-07-363560676-release-release/gmail-2021-03-07-363560676-release-2-android-apk-download/)\n* [2021.03.07.363022938.Release (universal)](https://www.apkmirror.com/apk/google-inc/gmail/gmail-2021-03-07-363022938-release-release/gmail-2021-03-07-363022938-release-android-apk-download/)\n* [2021.03.21.366143478.Release (universal)](https://www.apkmirror.com/apk/google-inc/gmail/gmail-2021-03-21-366143478-release-release/gmail-2021-03-21-366143478-release-android-apk-download/)\n\n<img src=\"https://pbs.twimg.com/media/EEK15orXkAErJm_?format=jpg\" width=\"30%\">\n<img src=\"https://pbs.twimg.com/media/EEK15olWwAALArs?format=jpg\" width=\"30%\"> \n<img src=\"https://pbs.twimg.com/media/EEK15otWkAAQ76o?format=jpg\" width=\"30%\">\n\n⚠️ The module will now be updated to support new versions on request only ⚠️<br>\nTo request an update send me a DM on Twitter or via email at support-android@alex193a.com ✉️\n","summary":"[Partially abandoned - READ THE DESCRIPTION]\nAllow to use the official dark theme in Gmail on Android 9 and earlier.","sourceUrl":"","hide":false,"additionalAuthors":[],"childGitHubReadme":{"childMarkdownRemark":{"excerpt":"Gmail Dark Theme Enabler Allow to use the official dark theme in Gmail on Android 9 and earlier. No configuration needed, install and restart the phone. Compatible versions: 2019.08.18.267044774.release 2019.09.01.268168002.release 2019.09.15.270135…"}}}},{"node":{"name":"com.alex193a.opcameradebug","description":"OnePlus Camera Debug Mode Enabler","url":"https://github.com/Xposed-Modules-Repo/com.alex193a.opcameradebug","homepageUrl":"https://twitter.com/alex193a","collaborators":{"edges":[{"node":{"login":"alex193a","name":"Alessandro Paluzzi"}}]},"readme":"# OnePlus Camera Debug Mode Enabler\n\nEnable the hidden internal menu in the OnePlus camera app.\n\nNo configuration needed, install and restart the phone.\n\nTested on a OnePlus 9 Pro with OnePlus Camera v6.2.36\n\n<img src=\"https://xposed.alex193a.com/wp-content/uploads/2021/04/Screenshot_20210413-000954-917x2048.jpg\" width=\"30%\">","summary":"Enable the hidden internal menu in the OnePlus camera app.","sourceUrl":"","hide":false,"additionalAuthors":[],"childGitHubReadme":{"childMarkdownRemark":{"excerpt":"OnePlus Camera Debug Mode Enabler Enable the hidden internal menu in the OnePlus camera app. No configuration needed, install and restart the phone. Tested on a OnePlus 9 Pro with OnePlus Camera v6.2.36"}}}},{"node":{"name":"com.coderstory.flyme9","description":"Flyme9助手","url":"https://github.com/Xposed-Modules-Repo/com.coderstory.flyme9","homepageUrl":"","collaborators":{"edges":[{"node":{"login":"coderstory","name":"CoderStory"}}]},"readme":"# Flyme9助手\nFlyme9助手是基于LSPosed开发的Flyme系统优化工具\n当前版本适用于flyme9系统,低版本的android系统可能部分功能不可使用。\n\n## 功能\n- 屏蔽魅族自家广告SDK的广告\n- 针对自家app隐藏root权限\n- 获取更新包下载地址\n- 安装apk的时候跳过安全检查\n- 默认自动安装apk\n- 主题和谐\n- 状态栏时间居中\n- 隐藏状态栏图标\n- 时间显秒\n- 冻结应用\n- 清理应用缓存\n- ...\n","summary":"Flyme系统定制修改工具","sourceUrl":null,"hide":false,"additionalAuthors":[{"name":"coderstory","link":"https://github.com/coderstory","type":"add"}],"childGitHubReadme":{"childMarkdownRemark":{"excerpt":"Flyme9助手 Flyme9助手是基于LSPosed开发的Flyme系统优化工具\n当前版本适用于flyme9系统,低版本的android系统可能部分功能不可使用。 功能 屏蔽魅族自家广告SDK的广告 针对自家app隐藏root权限 获取更新包下载地址 安装apk的时候跳过安全检查 默认自动安装apk 主题和谐 状态栏时间居中 隐藏状态栏图标 时间显秒 冻结应用 清理应用缓存 ..."}}}},{"node":{"name":"cn.lovesykun.miui_force_fps","description":"MIUI Force FPS / MIUI 全局高帧","url":"https://github.com/Xposed-Modules-Repo/cn.lovesykun.miui_force_fps","homepageUrl":"https://github.com/yujincheng08/MIUIForceFPS","collaborators":{"edges":[{"node":{"login":"yujincheng08","name":"LoveSy"}}]},"readme":"# cn.lovesykun.miui_force_fps\n","summary":"Force MIUI to have highest FPS globally\n强制 MIUI 全局高帧","sourceUrl":null,"hide":false,"additionalAuthors":null,"childGitHubReadme":{"childMarkdownRemark":{"excerpt":"cn.lovesykun.miui_force_fps"}}}},{"node":{"name":"chili.xposed.chimi","description":"ChiMi","url":"https://github.com/Xposed-Modules-Repo/chili.xposed.chimi","homepageUrl":"https://github.com/yonghen/chimi-/issues","collaborators":{"edges":[{"node":{"login":"JasonKhew96","name":"Jason_Khew"}}]},"readme":"# ChiMi #\nMIUI扩展插件（EdXposed/TaiChi/LSPosed）\n\n修改MIUI系统的一款MIUI增强插件\n\n\n最新版本只支持MIUI12.5\n\n失效的可以尝试：\n▲①用太极/EdXposed优化应用（如状态栏功能部分失效，用太极优化系统界面，Edxposed用Speed模式优化系统界面） \n\n②重新添加应用和重新勾选模块！\n\n③清除ChiMi数据或者重装ChiMi\n\n④太极阳用户要仔细看适配的版本，还没适配就会失效，适配后要更新太极阳引擎\n\n⑤停用可能起冲突的Xposed模块和Magisk模块（比如修改系统或者系统界面的Xposed/Magisk模块；停用/删除magisk模块后需要删除/data/system/package-cache/里对应文件）\n\n更多细节写在使用说明中\n\n如果按照软件内说明的操作过后还是不行的可以提交issue。\n\n更新后最好重新勾选并重启，避免出现未知bug。\n\n\n已知bug：\n- 锁屏时间样式选择第四个，添加闹钟失效\n- MIXAlpha充电特效每次重启第一次使用会错位。\n- 状态栏网络类型变大且移动位置至信号右边，双卡用户会出现留白现象\n- 因MIUI12.5状态栏的信号和状态栏系统图标（蓝牙、静音等）布局是动态布局，所以时间居中+信号居左会把系统图标也居左；\n切换横屏时挖孔屏时间居中，状态栏左边会留白一部分，且再切回竖屏时状态栏布局会乱，需要下拉刷新一下状态栏。\n\n\n\n功能如下图：\n![image](https://github.com/yonghen/chimi-/raw/master/img/1.jpg)\n![image](https://github.com/yonghen/chimi-/raw/master/img/2.jpg)\n![image](https://github.com/yonghen/chimi-/raw/master/img/3.jpg)\n![image](https://github.com/yonghen/chimi-/raw/master/img/4.jpg)\n![image](https://github.com/yonghen/chimi-/raw/master/img/5.jpg)\n![image](https://github.com/yonghen/chimi-/raw/master/img/6.jpg)","summary":"修改MIUI系统的一款 MIUI 增强插件","sourceUrl":"https://github.com/yonghen/chimi-","hide":false,"additionalAuthors":[],"childGitHubReadme":{"childMarkdownRemark":{"excerpt":"ChiMi MIUI扩展插件（EdXposed/TaiChi/LSPosed） 修改MIUI系统的一款MIUI增强插件 最新版本只支持MIUI12.5 失效的可以尝试：\n▲①用太极/EdXposed优化应用（如状态栏功能部分失效，用太极优化系统界面，Edxposed用Speed模式优化系统界面） ②重新添加应用和重新勾选模块！ ③清除ChiMi数据或者重装ChiMi ④太极阳用户要仔细看适配的版本，还没适配就会失效，适配后要更新太极阳引擎 ⑤停用可能起冲突的Xposed模块和Magisk模块（…"}}}},{"node":{"name":"com.alex193a.ivdisabler","description":"Integrity Verification Disabler","url":"https://github.com/Xposed-Modules-Repo/com.alex193a.ivdisabler","homepageUrl":"https://twitter.com/alex193a","collaborators":{"edges":[{"node":{"login":"alex193a","name":"Alessandro Paluzzi"}}]},"readme":"# Integrity Verification Disabler\n\nBypass the integrity verification introduced on Android 11 by allowing you to update the Google Camera to version 8.0+ on phones other than the Pixel 5.\n\nTested by installing the update via **ADB**.\n\nNo configuration needed, install and restart the phone.\n\nThe module is also available as a *Magisk Module*! You can download it from: [https://xposed.alex193a.com](https://xposed.alex193a.com)\n\n⚠️ The Magisk Module has been tested **ONLY** on a Pixel 3XL. Use it at your own risk. ⚠️","summary":"Google seems to be blocking sideloading some app updates on Android 11, such as the Google Camera v8.0+, this module bypass that block.","sourceUrl":"","hide":false,"additionalAuthors":[],"childGitHubReadme":{"childMarkdownRemark":{"excerpt":"Integrity Verification Disabler Bypass the integrity verification introduced on Android 11 by allowing you to update the Google Camera to version 8.0+ on phones other than the Pixel 5. Tested by installing the update via ADB. No configuration needed…"}}}},{"node":{"name":"moe.henry_zhr.force_dark","description":"Force Dark","url":"https://github.com/Xposed-Modules-Repo/moe.henry_zhr.force_dark","homepageUrl":"https://github.com/Henry-ZHR/force_dark","collaborators":{"edges":[{"node":{"login":"Henry-ZHR","name":"Henry Zhang"}}]},"readme":"为作用域内应用强制启用 SmartDark（又名 [Force Dark](https://developer.android.com/guide/topics/ui/look-and-feel/darktheme#force_dark)）\n\nAndroid 10+\n\n不保证在高度魔改的系统上能工作","summary":null,"sourceUrl":"https://github.com/Henry-ZHR/force_dark","hide":false,"additionalAuthors":null,"childGitHubReadme":{"childMarkdownRemark":{"excerpt":"为作用域内应用强制启用 SmartDark（又名 Force Dark） Android 10+ 不保证在高度魔改的系统上能工作"}}}},{"node":{"name":"sb.firefds.r.firefdskit","description":"Firefds Kit [R]","url":"https://github.com/Xposed-Modules-Repo/sb.firefds.r.firefdskit","homepageUrl":"https://forum.xda-developers.com/t/xposed-r-firefds-kit-1-0-0-0-alpha-1-customize-samsung-oneui-3-0-02-01-21.4212051/","collaborators":{"edges":[{"node":{"login":"Firefds","name":"Shauli Bracha"}}]},"readme":"# Firefds Kit [R]\n\nXposed module for Samsung R (Android 11) devices.\n\n## Features\nThe module has the following features:\n- Fake system status to Official\n- Custom advanced power menu options:\n  - Power off\n  - Restart\n  - Emergency mode\n  - Recovery\n  - Download\n  - Data mode switch\n  - Screenshot\n  - Switch User (when multi user is enabled)\n  - SystemUI restart\n  - Flashlight\n  - Screen Recorder (requires Samsung screen recorder app installed)\n- Disable restart confirmation\n- Enable call recording\n- Replace add call button instead of call recording\n- Enable call recording from menu\n- Auto call recording\n- Hide VoLTE icon in status bar\n- Hide persistent USB connection notification\n- Hide persistent charging notification\n- Enable block phrases in messages app settings\n- Enable native blur on notification panel pull down\n- Enable multi user toggle\n- Set max user value selector\n- Show seconds in status bar clock toggle\n- Show clock date on right of clock toggle\n- Add date to status bar clock options\n- Enable biometrics and fingerprints unlock on reboot toggle\n- Add network speed menu to show network speed in the status bar\n- Data icon symbol selection (4G, LTE, 4G+, 4.5G)\n- Show Data usage view in quick panel\n- Double tap for sleep\n- Hide NFC icon\n- Disable Bluetooth toggle popup\n- Disable sync toggle popup\n- Disable high level brightness poup\n- Hide carrier label\n- Carrier label size selection\n- Disable loud volume warning\n- Disable volume control sound\n- Disable low battery sound\n- Screen timeout settings\n- NFC behavior settings\n- Auto MTP\n- Disable camera temperature check\n- Enable camera shutter sound menu\n- Disable call number formatting\n- Disable SMS to MMS threshold\n- Force MMS connect\n- Bypass exchange security (currently not working)\n- Disable signature check\n- Disable secure flag\n\n## Attention\nThis version was tested by the community and not by me, as I don't have an Android 11 Samsung device.\n**THERE COULD BE BUGS/CRASHES/BOOTLOOPS**, but it's pretty stable.\nPlease upload any xposed logs when you encounter any issue. I can't help you without the logs!\nConfirmed working on:\n- Galaxy S20\n- Galaxy S10\n\n## Installation\n\nTo install this module you need the following apps and modules installed on your device:\n1. Magisk v21.2 and above - https://github.com/topjohnwu/Magisk/releases\n2. Magisk Manager v8.0.4 and above - https://github.com/topjohnwu/Magisk/releases\n3. Riru Magisk module v23.1 and above - https://github.com/RikkaApps/Riru/releases\n4. LSPosed Magisk module v0.5.4.0 and above - https://github.com/LSPosed/LSPosed/releases\n5. LSPosed Manager v0.5.4.0 and above - https://github.com/LSPosed/LSPosed/releases\n\n## Known Issues\n\n- Some features are removed on purpose. Since GravityBox has been working on Samsung Oreo devices without much issues, I only implemented features that need special Samsung coding. You can check You can check GravityBox for R, when it will become available, for additional features.\n\n## External Libraries\n\nThe project uses the following libraries:\n1. https://github.com/rovo89/XposedBridge\n2. https://github.com/rovo89/XposedMods/tree/master/XposedLibrary\n3. Samsung framework libraries which are used for compile only\n\n## Credits\nThis module wouldn't have been here without the following people:\n- [RikkaW](https://github.com/RikkaApps) - Creator of Riru Magisk module, which provides a way to inject codes into zygote process\n- [rovo89](https://github.com/rovo89) - Creator of the original Xposed framework APIs\n- [solohsu](https://github.com/solohsu) and [MlgmXyysd](https://github.com/MlgmXyysd) - Creators of the EdXposed Magisk module and Installer that made all of this possible\n- [C3C0](https://github.com/GravityBox) - Creator of GravityBox Xposed modules, which I learnt a lot from\n- [Wanam](https://github.com/wanam) - Creator of the original XTouchWiz module, which this module is based on.\n- [topjohnwu](https://github.com/topjohnwu) - Creator of Magisk\n- [AbrahamGC](https://forum.xda-developers.com/member.php?u=7393522) - [For the Extended Power Menu - Pie - Odex framework Smali guide](https://forum.xda-developers.com/showpost.php?p=78910083&postcount=944)\n- Big thank you to [m8980](https://forum.xda-developers.com/m/m8980.1614889) and [ianmacd](https://forum.xda-developers.com/m/ianmacd.7187684) for testing countless versions and sending xposed logs\n\nThis is a moded version of Wanam's XTouchWiz:\nhttps://github.com/wanam/XTouchWiz\n\n## Telegram\nAnnouncements and pre release versions - https://t.me/firefdskit\n","summary":"Firefds Kit Xposed module for Samsung R (Android 11) devices","sourceUrl":"https://github.com/Firefds/FirefdsKit/tree/R","hide":false,"additionalAuthors":[],"childGitHubReadme":{"childMarkdownRemark":{"excerpt":"Firefds Kit [R] Xposed module for Samsung R (Android 11) devices. Features The module has the following features: Fake system status to Official Custom advanced power menu options: Power off Restart Emergency mode Recovery Download Data mode switch …"}}}},{"node":{"name":"sb.firefds.q.firefdskit","description":"Firefds Kit [Q]","url":"https://github.com/Xposed-Modules-Repo/sb.firefds.q.firefdskit","homepageUrl":"https://forum.xda-developers.com/xposed/modules/xposed-firefds-kit-0-0-1-0-alpha-1-t4044757","collaborators":{"edges":[{"node":{"login":"Firefds","name":"Shauli Bracha"}}]},"readme":"# Firefds Kit [Q]\n\nXposed module for Samsung Q (Android 10) devices.\n\n## Features\nThe module has the following features:\n- Fake system status to Official\n- Custom advanced power menu options:\n  - Power off\n  - Restart\n  - Emergency mode\n  - Recovery\n  - Download\n  - Data mode switch\n  - Screenshot\n  - Switch User (when multi user is enabled)\n  - SystemUI restart\n  - Flashlight\n  - Screen Recorder (requires Samsung screen recorder app installed)\n- Disable restart confirmation\n- Enable call recording\n- Replace add call button instead of call recording\n- Enable call recording from menu\n- Auto call recording\n- Hide VoLTE icon in status bar\n- Hide persistent USB connection notification\n- Hide persistent charging notification\n- Enable block phrases in messages app settings\n- Enable native blur on notification panel pull down\n- Enable multi user toggle\n- Set max user value selector\n- Show seconds in status bar clock toggle\n- Show clock date on right of clock toggle\n- Add date to status bar clock options\n- Enable biometrics and fingerprints unlock on reboot toggle\n- Add network speed menu to show network speed in the status bar\n- Data icon symbol selection (4G, LTE, 4G+, 4.5G)\n- Show Data usage view in quick panel\n- Double tap for sleep\n- Hide NFC icon\n- Disable Bluetooth toggle popup\n- Disable sync toggle popup\n- Disable high level brightness poup\n- Hide carrier label\n- Carrier label size selection\n- Disable loud volume warning\n- Disable volume control sound\n- Disable low battery sound\n- Screen timeout settings\n- NFC behavior settings\n- Auto MTP\n- Disable camera temperature check\n- Enable camera shutter sound menu\n- Disable call number formatting\n- Disable SMS to MMS threshold\n- Force MMS connect\n- Bypass exchange security\n- Disable signature check\n- Disable secure flag\n\n## Attention\nThis version was tested by the community and not by me, as I don't have an Android 10 Samsung device.\n**THERE COULD BE BUGS/CRASHES/BOOTLOOPS**, but it's pretty stable.\nPlease upload any xposed logs when you encounter any issue. I can't help you without the logs!\nConfirmed working on:\n- Galaxy S9\n- Note 9\n- Galaxy S10\n\n## Installation\n\nTo install this module you need the following apps and modules installed on your device:\n1. Magisk v19 and above - https://github.com/topjohnwu/Magisk/releases\n2. Magisk Manager v7.5.1 and above - https://github.com/topjohnwu/Magisk/releases\n3. Riru Magisk module v19.6 and above - https://github.com/RikkaApps/Riru/releases\n4. LSPosed v0.5.4.0 and above - https://github.com/LSPosed/LSPosed/releases\n\n## Known Issues\n\n- Some features are removed on purpose. Since GravityBox has been working on Samsung Oreo devices without much issues, I only implemented features that need special Samsung coding. You can check [GravityBox for Q](https://forum.xda-developers.com/xposed/modules/app-gravitybox-v10-0-0-beta-1-android-10-t3974497) for additional features.\n- Changes between EdXposed versions 4xxx and 5xxx will result in app settings lost.\n## External Libraries\n\nThe project uses the following libraries:\n1. https://github.com/topjohnwu/libsu\n2. https://github.com/rovo89/XposedBridge\n3. https://github.com/rovo89/XposedMods/tree/master/XposedLibrary\n5. Samsung framework libraries which are used for compile only\n\n## Credits\nThis module wouldn't have been here without the following people:\n- [RikkaW](https://github.com/RikkaApps) - Creator of Riru Magisk module, which provides a way to inject codes into zygote process\n- [rovo89](https://github.com/rovo89) - Creator of the original Xposed framework APIs\n- [solohsu](https://github.com/solohsu) and [MlgmXyysd](https://github.com/MlgmXyysd) - Creators of the EdXposed Magisk module and Installer that made all of this possible\n- [C3C0](https://github.com/GravityBox) - Creator of GravityBox Xposed modules, which I learnt a lot from\n- [Wanam](https://github.com/wanam) - Creator of the original XTouchWiz module, which this module is based on.\n- [topjohnwu](https://github.com/topjohnwu) - Creator of Magisk\n- [AbrahamGC](https://forum.xda-developers.com/member.php?u=7393522) - [For the Extended Power Menu - Pie - Odex framework Smali guide](https://forum.xda-developers.com/showpost.php?p=78910083&postcount=944)\n\nThis is a moded version of Wanam's XTouchWiz:\nhttps://github.com/wanam/XTouchWiz\n\n## Telegram\nAnnouncements and pre release versions - https://t.me/firefdskit\n","summary":"Firefds Kit Xposed module for Samsung Q (Android 10) devices","sourceUrl":"https://github.com/Firefds/FirefdsKit/tree/Q","hide":false,"additionalAuthors":[],"childGitHubReadme":{"childMarkdownRemark":{"excerpt":"Firefds Kit [Q] Xposed module for Samsung Q (Android 10) devices. Features The module has the following features: Fake system status to Official Custom advanced power menu options: Power off Restart Emergency mode Recovery Download Data mode switch …"}}}},{"node":{"name":"com.coderstory.flyme","description":"Flyme8助手","url":"https://github.com/Xposed-Modules-Repo/com.coderstory.flyme","homepageUrl":"","collaborators":{"edges":[{"node":{"login":"coderstory","name":"CoderStory"}}]},"readme":"# Flyme8助手\nFlyme8助手是基于LSPosed开发的Flyme系统优化工具\n当前版本适用于flyme8.x系统,低版本的android系统可能部分功能不可使用。\n\n## 功能\n- 屏蔽魅族自家广告SDK的广告\n- 针对自家app隐藏root权限\n- 获取更新包下载地址\n- 安装apk的时候跳过安全检查\n- 默认自动安装apk\n- 主题和谐\n- 状态栏时间居中\n- 隐藏状态栏图标\n- 时间显秒\n- 冻结应用\n- 清理应用缓存\n- ...\n","summary":"Flyme系统定制修改工具","sourceUrl":null,"hide":false,"additionalAuthors":[{"name":"coderstory","link":"https://github.com/coderstory","type":"add"}],"childGitHubReadme":{"childMarkdownRemark":{"excerpt":"Flyme8助手 Flyme8助手是基于LSPosed开发的Flyme系统优化工具\n当前版本适用于flyme8.x系统,低版本的android系统可能部分功能不可使用。 功能 屏蔽魅族自家广告SDK的广告 针对自家app隐藏root权限 获取更新包下载地址 安装apk的时候跳过安全检查 默认自动安装apk 主题和谐 状态栏时间居中 隐藏状态栏图标 时间显秒 冻结应用 清理应用缓存 ..."}}}},{"node":{"name":"sb.firefds.pie.firefdskit","description":"Firefds Kit [P]","url":"https://github.com/Xposed-Modules-Repo/sb.firefds.pie.firefdskit","homepageUrl":"https://forum.xda-developers.com/xposed/modules/xposed-firefds-kit-customization-t3908114","collaborators":{"edges":[{"node":{"login":"Firefds","name":"Shauli Bracha"}}]},"readme":"# Firefds Kit [Pie]\n\nXposed module for Samsung Pie (Android 9) devices. \n\n## Features\nThe module has the following features:\n- Fake system status to Official\n- Selectable advanced power menu options:\n  - Power off\n  - Restart\n  - Emergency mode\n  - Recovery\n  - Download\n  - Data mode switch\n  - Screenshot\n  - Switch User (when multi user is enabled)\n  - SystemUI restart\n  - Flashlight\n  - Screen Recorder (requires Samsung screen recorder app installed)\n- Disable restart confirmation\n- Enable call recording\n- Replace add call button instead of call recording\n- Enable call recording from menu\n- Auto call recording\n- Hide VoLTE icon in status bar\n- Hide persistent USB connection notification\n- Hide persistent charging notification\n- Enable block phrases in messages app settings\n- Enable native blur on notification panel pull down\n- Enable navigation bar color settings in Navigation Bar settings\n- Navigation bar custom color picker\n- Enable multi user toggle\n- Set max user value selector\n- Show seconds in status bar clock toggle\n- Show clock date on right of clock toggle\n- Add date to status bar clock options\n- Enable fingerprint unlock on reboot toggle\n- Enable biometrics unlock on reboot toggle\n- Add network speed menu to show network speed in the status bar\n- Data icon symbol selection (4G, LTE, 4G+, 4.5G)\n- Show Data usage view in quick panel\n- Double tap for sleep\n- Hide NFC icon\n- Disable Bluetooth toggle popup\n- Disable sync toggle popup\n- Disable high level brightness poup\n- Hide carrier label\n- Carrier label size selection\n- Disable loud volume warning\n- Disable volume control sound\n- Disable low battery sound\n- Screen timeout settings\n- NFC behavior settings\n- Auto MTP\n- Disable camera temperature check\n- Enable camera shutter sound menu\n- Disable call number formatting\n- Disable SMS to MMS threshold\n- Force MMS connect\n- Bypass exchange security\n- Disable signature check\n- Disable secure flag\n\n## Attention\nThis was built and tested on the Samsung Galaxy S8 G950F (Exynos) varient.\nConfirmed working on:\n- Galaxy S8\n- Galaxy S8+\n- Galaxy Note 8\n- Galaxy S9\n- Galaxy Note 9\n- Galaxy S10\n- Galaxy S10+\n- Galaxy Tab S4\n\n**THERE COULD BE BUGS/CRASHES/BOOTLOOPS**, but it's pretty stable.\nI've been working with both solohsu and C3C0 on testing EdXposed on Samsung devices.\n\n## Major Update\n\nIn the Pie version of FirefdsKit, I have updates the project in the following aspects:\n1. Moved project from Eclipse to Android Studio\n2. Updated compile SDK version to use latest SDK (28)\n3. Updated dependencies to use online sources\n\n## Installation\n\nTo install this module you need the following apps and modules installed on your device:\n1. Magisk v18.1 and above - https://github.com/topjohnwu/Magisk/releases\n2. Magisk Manager v7.0.0 and above - https://github.com/topjohnwu/Magisk/releases\n3. Riru Magisk module v16.0 and above - https://github.com/RikkaApps/Riru/releases\n4. EdXposed Magisk module v0.3.0.0_beta2 and above - https://github.com/ElderDrivers/EdXposed/releases\n5. EdXposed Installer v2.2.1 and above - https://github.com/solohsu/XposedInstaller/releases\n\n## Known Issues\n\n- Some features are removed on purpose. Since GravityBox has been working on Samsung Oreo devices without much issues, I only implemented features that need special Samsung coding. You can check [GravityBox for Pie](https://forum.xda-developers.com/xposed/modules/app-gravitybox-v9-0-0-beta-1-android-9-t3908768) for additional features.\n- It could take some time to popup the root request, just wait a few minutes until it pops up, usually not much after the xposed installer recognized the module.\n\n## External Libraries\n\nThe project uses the following libraries:\n1. https://github.com/topjohnwu/libsu\n2. https://github.com/rovo89/XposedBridge\n3. https://github.com/rovo89/XposedMods/tree/master/XposedLibrary\n4. https://github.com/jaredrummler/ColorPicker\n5. Samsung framework libraries which are used for compile only\n\n## Credits\nThis module wouldn't have been here without the following people:\n- [RikkaW](https://github.com/RikkaApps) - Creator of Riru Magisk module, which provides a way to inject codes into zygote process\n- [rovo89](https://github.com/rovo89) - Creator of the original Xposed framework APIs\n- [solohsu](https://github.com/solohsu) and [MlgmXyysd](https://github.com/MlgmXyysd) - Creators of the EdXposed Magisk module and Installer that made all of this possible\n- [C3C0](https://github.com/GravityBox) - Creator of GravityBox Xposed modules, which I learnt a lot from\n- [Wanam](https://github.com/wanam) - Creator of the original XTouchWiz module, which this module is based on.\n- [topjohnwu](https://github.com/topjohnwu) - Creator of Magisk\n- [AbrahamGC](https://forum.xda-developers.com/member.php?u=7393522) - [For the Extended Power Menu - Pie - Odex framework Smali guide](https://forum.xda-developers.com/showpost.php?p=78910083&postcount=944)\n- [jaredrummler](https://github.com/jaredrummler) - For Color Picker library\n\nThis is a moded version of Wanam's XTouchWiz:\nhttps://github.com/wanam/XTouchWiz\n\n## Telegram\nAnnouncements and pre release versions - https://t.me/firefdskit\n","summary":"Firefds Kit Xposed module for Samsung Pie (Android 9) devices","sourceUrl":"https://github.com/Firefds/FirefdsKit/tree/pie","hide":false,"additionalAuthors":[],"childGitHubReadme":{"childMarkdownRemark":{"excerpt":"Firefds Kit [Pie] Xposed module for Samsung Pie (Android 9) devices. Features The module has the following features: Fake system status to Official Selectable advanced power menu options: Power off Restart Emergency mode Recovery Download Data mode …"}}}},{"node":{"name":"com.crossbowffs.quotelock","description":"QuoteLock","url":"https://github.com/Xposed-Modules-Repo/com.crossbowffs.quotelock","homepageUrl":"https://github.com/apsun/QuoteLock","collaborators":{"edges":[{"node":{"login":"soumyamahunt","name":"Soumya Ranjan Mahunt"}}]},"readme":"# QuoteLock\n\n[Displays quotes on your phone lockscreen!](https://i.imgur.com/EXzpNWA.jpg) Why, you ask? Well, why not?!\n\n**PLEASE READ BEFORE INSTALLING:**\n\n**Only near-AOSP Android ROMs (e.g. Nexus, Moto, OnePlus) are supported!** This is due to the heavy modifications that many OEMs make to the lockscreen. Feel free to try it on your phone, but don't be surprised if the layout is broken.\n\n**After installing, please open the app at least once** to allow the quote downloader service to run in the background.\n\n**If you are using Prevent Running (阻止运行/ForceStopGB) or other task killing apps, you must whitelist QuoteLock!** Otherwise, you may experience problems with the quote not refreshing or failing to load.\n\nSupported quote sources:\n\n* [Visual Novel as a Service (日本語)](http://vnaas.apsun.xyz/)\n* [Hitokoto (unofficial) (中文)](https://blog.lwl12.com/read/hitokoto-api.html)\n* [Goodreads QotD (English)](https://www.goodreads.com/)\n* [Wikiquote QotD (中文)](https://www.wikiquote.org/)\n* [Freakuotes (Español)](https://freakuotes.com/)\n* [Natune.net (Deutsch)](https://natune.net/zitate/)\n* [BrainyQuote (English)](https://www.brainyquote.com/)\n* None of these fit you? You can even write your own!\n\nAuthor(s): [crossbowffs](https://repo.xposed.info/users/crossbowffs) <br />\nSupport/Discussion URL: \nhttps://github.com/apsun/QuoteLock <br />\nSource code URL: \nhttps://github.com/apsun/QuoteLock <br />\nPackage: \n[com.crossbowffs.quotelock](https://github.com/Xposed-Modules-Repo/com.crossbowffs.quotelock/releases/tag/1.4.0)\n","summary":"Displays quotes on your phone lockscreen!","sourceUrl":"https://github.com/apsun/QuoteLock","hide":false,"additionalAuthors":[{"name":"apsun","link":null,"type":"add"},{"name":"soumyamahunt","link":null,"type":"remove"}],"childGitHubReadme":{"childMarkdownRemark":{"excerpt":"QuoteLock Displays quotes on your phone lockscreen! Why, you ask? Well, why not?! PLEASE READ BEFORE INSTALLING: Only near-AOSP Android ROMs (e.g. Nexus, Moto, OnePlus) are supported! This is due to the heavy modifications that many OEMs make to the…"}}}},{"node":{"name":"com.ceco.oreo.gravitybox","description":"GravityBox [O]","url":"https://github.com/Xposed-Modules-Repo/com.ceco.oreo.gravitybox","homepageUrl":"https://forum.xda-developers.com/showthread.php?t=3739929","collaborators":{"edges":[{"node":{"login":"C3C0","name":null}}]},"readme":"# GravityBox [O]\n\n**GravityBox** is a module which primary goal is to provide the users of devices running vanilla or close to vanilla Android\n\nwith a tweak box that turns their stock ROM into a custom ROM packed with additional features and tweaks;\n\nwithout the need of flashing a custom ROM. Most of the preferences can be changed on-the-fly without rebooting.\n\n***THIS VERSION IS FOR OREO ROMs***\n- For Lollipop, use GravityBox [LP]\n- For KitKat, use GravityBox [KK]\n- For JellyBean, use GravityBox [JB]\n- For Marshmallow, use GravityBox [MM]\n- For Nougat, use GravityBox [N]\n\n## Main features\n- QuickSettings tile management with additional tiles\n- Pie Controls\n- Expanded desktop with semi-immersive and immersive modes\n- Lockscreen tweaks\n- Statusbar tweaks\n- Navigation bar tweaks\n- Power tweaks\n- Display tweaks\n- Media tweaks\n- Phone tweaks\n- Hardware key actions\n- Launcher tweaks\n- Screen recording\n- Smart radio\n- Notification control (per-app notification LED/sounds/vibrations)\n- Fingerprint Launcher\n- Advanced tuning of Framework and System UI parameters\n\n... and many more\n\n## Compatibility\n- Supports AOSP devices running vanilla Android Oreo 8.0/8.1\n- Supports OnePlus 3T running official OOS 5.0.1\n- DOES NOT support devices running ROMs vastly modified by device manufacturers (HTC Sense, LG, Samsung Touchwiz, MIUI, LeWa, Xperia, ...)\n- SHOULD NOT be used with custom ROMs like Lineage, AOSPA, or any other derivative - it makes no sense since the most of the features are already in the ROM (may cause conflicts and unexpected behavior)\n\n## EdXposed compatibility\nGravityBox requires EdXposed v0.4 or later with resource hooking support\n\n## Info about premium features and PayPal transaction ID verification system\n1. Those who supported development via PayPal donation can use their PayPal transaction ID to unlock premium features. Currently there are two premium features: 1) Backup/restore of GB settings 2) Ultimate notification control\n\n2. If you contributed to the project by providing translations, code fragments, or by any other way. You can apply for a free transaction ID by contacting me via PM @ forum.xda-developers.com\n\n3. Be aware that there's a system that can identify potential transaction ID abuse. E.g. when one ID is being used by more users. Such IDs will get blocked automatically. This can also happen when you previously exposed your ID in public forum and other users took advantage of it. If this is the case, contact me via PM so I can issue new, special ID. In case you own more devices, you can use one transaction ID on up to 10 of them.\n\n4. If you are using your own custom builds of GB for personal use, you will get hash mismatch upon verifying your ID as verification system accepts requests only from official releases of GB. If you want to be able to verify IDs with your custom build, contact me via PM so I can setup a special hash for your build. If you are using a custom build that you provide for broader group of users (e.g. in a custom ROM), It is necessary to ask for new hash everytime your new custom version is released for public use. These rules are based on mutual trust so please, do not violate them.\n\nDonation is also possible by purchasing GravityBox Unlocker from the Play Store\n","summary":"All-in-one complex module for devices running vanilla Android 8 Oreo","sourceUrl":"https://github.com/GravityBox/GravityBox/tree/oreo-as-edxposed","hide":false,"additionalAuthors":[],"childGitHubReadme":{"childMarkdownRemark":{"excerpt":"GravityBox [O] GravityBox is a module which primary goal is to provide the users of devices running vanilla or close to vanilla Android with a tweak box that turns their stock ROM into a custom ROM packed with additional features and tweaks; without…"}}}},{"node":{"name":"com.ceco.pie.gravitybox","description":"GravityBox [P]","url":"https://github.com/Xposed-Modules-Repo/com.ceco.pie.gravitybox","homepageUrl":"https://forum.xda-developers.com/showthread.php?t=3908768","collaborators":{"edges":[{"node":{"login":"C3C0","name":null}}]},"readme":"# GravityBox [P]\n\n**GravityBox** is a module which primary goal is to provide the users of devices running vanilla or close to vanilla Android\n\nwith a tweak box that turns their stock ROM into a custom ROM packed with additional features and tweaks;\n\nwithout the need of flashing a custom ROM. Most of the preferences can be changed on-the-fly without rebooting.\n\n## !!!!!! WARNING !!!!!!\nThis module utilizes EdXposed Framework which is still in early development stage and may contain bugs or might not be fully compatible with system of your Android device. I take no responsibility for any issues arising from using GravityBox with EdXposed and strongly recommend creating a full backup of your device before activating the module.\n\n***THIS VERSION IS FOR PIE ROMs***\n- For Lollipop, use GravityBox [LP]\n- For KitKat, use GravityBox [KK]\n- For JellyBean, use GravityBox [JB]\n- For Marshmallow, use GravityBox [MM]\n- For Nougat, use GravityBox [N]\n- For Oreo, use GravityBox [O]\n\n## Main features\n- QuickSettings tile management with additional tiles\n- Pie Controls\n- Expanded desktop with semi-immersive and immersive modes\n- Lockscreen tweaks\n- Statusbar tweaks\n- Navigation bar tweaks\n- Power tweaks\n- Display tweaks\n- Media tweaks\n- Phone tweaks\n- Hardware key actions\n- Launcher tweaks\n- Screen recording\n- Smart radio\n- Notification control (per-app notification LED/sounds/vibrations)\n- Fingerprint Launcher\n- Advanced tuning of Framework and System UI parameters\n\n... and many more\n\n## Compatibility\n- Supports AOSP devices running vanilla Android Pie 9\n- Supports OnePlus devices running official OxygenOS\n- Supports Pixel devices running official Google OS\n- *DOES NOT* support devices running ROMs vastly modified by device manufacturers (HTC Sense, LG, Samsung Touchwiz, MIUI, LeWa, Xperia, ...)\n- *SHOULD NOT* be used with custom ROMs like Lineage, AOSPA, or any other derivative - it makes no sense since the most of the features are already in the ROM (may cause conflicts and unexpected behavior)\n\n## Requirements\n- Magisk v19 or later\n- Riru core v19 or later (Magisk module)\n- Riru - EdXposed v0.4 or later (Magisk module; YAHFA or Sandhook whatever works best on your device)\n- EdXposed Installer\n\n## Info about premium features and PayPal transaction ID verification system\n1. Those who supported development via PayPal donation can use their PayPal transaction ID to unlock premium features. Currently there are two premium features: 1) Backup/restore of GB settings 2) Ultimate notification control\n\n2. If you contributed to the project by providing translations, code fragments, or by any other way. You can apply for a free transaction ID by contacting me via PM @ forum.xda-developers.com\n\n3. Be aware that there's a system that can identify potential transaction ID abuse. E.g. when one ID is being used by more users. Such IDs will get blocked automatically. This can also happen when you previously exposed your ID in public forum and other users took advantage of it. If this is the case, contact me via PM so I can issue new, special ID. In case you own more devices, you can use one transaction ID on up to 10 of them.\n\n4. If you are using your own custom builds of GB for personal use, you will get hash mismatch upon verifying your ID as verification system accepts requests only from official releases of GB. If you want to be able to verify IDs with your custom build, contact me via PM so I can setup a special hash for your build. If you are using a custom build that you provide for broader group of users (e.g. in a custom ROM), It is necessary to ask for new hash everytime your new custom version is released for public use. These rules are based on mutual trust so please, do not violate them.\n\nDonation is also possible by purchasing GravityBox Unlocker from the Play Store\n","summary":"All-in-one complex module for devices running vanilla Android 9 Pie","sourceUrl":"https://github.com/GravityBox/GravityBox/tree/pie","hide":false,"additionalAuthors":[],"childGitHubReadme":{"childMarkdownRemark":{"excerpt":"GravityBox [P] GravityBox is a module which primary goal is to provide the users of devices running vanilla or close to vanilla Android with a tweak box that turns their stock ROM into a custom ROM packed with additional features and tweaks; without…"}}}},{"node":{"name":"com.xposed.miuiime","description":"Unlock MIUI IME/解锁 MIUI 键盘优化","url":"https://github.com/Xposed-Modules-Repo/com.xposed.miuiime","homepageUrl":"https://github.com/RC1844/MIUI_IME_Unlock","collaborators":{"edges":[{"node":{"login":"RC1844","name":"RC1844"}},{"node":{"login":"keta1","name":"Ketal"}}]},"readme":"# MIUI IME Unlock\n\n解锁 MIUI 全面屏优化限制\n\n## 测试环境\n\nLSPosed v1.2.2(API 93.0)\n\nMUI 12.5\n\nAndroid 11(R,API 30)\n\n## 使用方法\n\nXposed API Version >= 93\n\n在作用域勾选需要解除限制的输入法即可，小米定制版也要勾上\n\n## 下载\n\n[app-release.apk](https://github.com/RC1844/MIUI_IME_Unlock/releases)\n\n## 特别说明\n\n1. 全面屏优化与百度输入法官方版存在兼容问题，这不属于本模块 BUG。\n2. 因为本人在用的是 MIUI12.5、Android11，所以对于其他版本的 MIUI 适配并不完整，存在不可用的可能性。\n3. ~~托盘按钮设置为小爱语音输入时，按钮失效不可用，目前未发现原因，但通过长按选择启动小爱似乎没有问题。~~\n4. 不接受任何为特定输入法适配 xxx 的请求，这不现实不合理。\n5. 使用了小白条沉浸模块的系统，可能在部分输入法上无法使用全面屏优化(郑重声明：这事关我屁事)\n\n## 更新日志\n\nv1.08\n\n    删除一个hook函数，解决重复hook\n    整理代码\n\nv1.07\n\n    增加检查prop ro.miui.support_miui_ime_bottom\n    底部按钮改为反色按钮\n    尝试在安卓9使用与安卓10相同的hook方法\n\nv1.06\n\n    更换检查MIUI版本为检查Android版本\n    删除旧方法依赖的代码\n\nv1.05\n\n    感谢 @ketal178 帮忙删除无用的代码\n    删除一些非必要的Hook\n    删除一些过时的代码\n    尝试修复小爱语音输入按钮失效问题\n\nv1.04\n\n    对 MIUI12 改回使用旧的hook点\n\nv1.03\n\n    加入对 MIUI 版本的检查\n    修复 MIUI12 输入法切换菜单不全的问题\n    现在仅对 MIUI12、MIUI12.5 生效\n\nv1.02\n\n    优化执行逻辑\n    部分hook方法不会对定制版进行hook\n    增加对底视图颜色的修改，颜色完全由输入法控制\n","summary":"Unlock MIUI Enhance keyboard\n解锁 MIUI 全面屏优化限制","sourceUrl":"https://github.com/RC1844/MIUI_IME_Unlock","hide":false,"additionalAuthors":[],"childGitHubReadme":{"childMarkdownRemark":{"excerpt":"MIUI IME Unlock 解锁 MIUI 全面屏优化限制 测试环境 LSPosed v1.2.2(API 93.0) MUI 12.5 Android 11(R,API 30) 使用方法 Xposed API Version >= 93 在作用域勾选需要解除限制的输入法即可，小米定制版也要勾上 下载 app-release.apk 特别说明 全面屏优化与百度输入法官方版存在兼容问题，这不属于本模块 BUG。 因为本人在用的是 MIUI12.5、Android11，所以对于其他版本的 MI…"}}}},{"node":{"name":"com.programminghoch10.mobileiconchanger","description":"MobileIconChanger (Fake5GIcon)","url":"https://github.com/Xposed-Modules-Repo/com.programminghoch10.mobileiconchanger","homepageUrl":"https://github.com/programminghoch10/MobileIconChanger","collaborators":{"edges":[{"node":{"login":"programminghoch10","name":null}}]},"readme":"# [MobileIconChanger](https://github.com/programminghoch10/MobileIconChanger)\nChange your mobile data icons! For example you can change the 3G/4G icons into 5G!\n\nThis module enables you to replace any of the mobile data icons with any other mobile data icon.\n\n## Compatibility\n\nAny AOSP near ROM should be compatible. Just try it out and see if it works. \n\n[Read more about compatiblity here](https://github.com/programminghoch10/MobileIconChanger#compatibility).\n\n## Installation\n\n1. Install the module on a system with a running XPosed framework with API version `>=93`.\n1. **Activate the resource hooks** within your XPosed framework manager.\n1. Activate the module. The package `SystemUI` should automatically be selected.\n1. Restart your phone.\n1. You are now ready to use the module. You will need to open the [Configuration](#configuration) screen to set it all up, as the module won't do anything yet.\n\n## Configuration\n\n_I don't like it when every XPosed module adds yet another app icon to the launcher. This is why this modules settings are hidden within the App-Info screen._\n\nHere is how to open the settings:\n\n- Route 1:\n    - Go to the module list within your XPosed manager\n    - Long press on `CameraControl` and select App Info\n    - On the bottom, click on `Advanced`\n    - Click on `Additional settings in the app`\n- Route 2:\n    - Go into device settings\n    - Click on apps\n    - Somehow tell the device to show all apps\n    - Select `CameraControl`\n    - On the bottom, click on `Advanced`\n    - Click on `Additional settings in the app`\n- Route 3:\n    - Open up an ADB shell\n    - Run command `am start-activity com.programminghoch10.mobileiconchanger/.SettingsActivity`\n\n## More resources\n\nI don't want to keep 4 different places up to date.\n\nIf you want to read more about \n[why this module exists](https://github.com/programminghoch10/MobileIconChanger#inspiration)\nor [additional info about the configuration interface](https://github.com/programminghoch10/MobileIconChanger#configuration)\nor [you just want to see some screenshots first](https://github.com/programminghoch10/MobileIconChanger#screenshots)\nhead over to [the GitHub Repo](https://github.com/programminghoch10/MobileIconChanger).\n","summary":"Change your mobile data icons! For example you can change the 3G/4G icons into 5G!","sourceUrl":"https://github.com/programminghoch10/MobileIconChanger","hide":false,"additionalAuthors":null,"childGitHubReadme":{"childMarkdownRemark":{"excerpt":"MobileIconChanger Change your mobile data icons! For example you can change the 3G/4G icons into 5G! This module enables you to replace any of the mobile data icons with any other mobile data icon. Compatibility Any AOSP near ROM should be compatibl…"}}}},{"node":{"name":"com.variable.apkhook","description":"应用伪装","url":"https://github.com/Xposed-Modules-Repo/com.variable.apkhook","homepageUrl":"https://www.coolapk.com/u/1195098","collaborators":{"edges":[{"node":{"login":"SekiBetu","name":"惜别"}}]},"readme":"# com.variable.apkhook\n\n[![](https://img.shields.io/github/v/release/Xposed-Modules-Repo/com.variable.apkhook)](https://github.com/Xposed-Modules-Repo/com.variable.apkhook/releases/latest)\n[![](https://img.shields.io/github/downloads/Xposed-Modules-Repo/com.variable.apkhook/total)](https://img.shields.io/github/downloads/Xposed-Modules-Repo/com.variable.apkhook/total)\n\n## Module name\n\n应用伪装\n\n## Author\n\n酷安@[暢越神密枫](https://www.coolapk.com/u/1195098)\n\nQQ交流群：742185295\n\n## Description\n功能与 [应用变量](https://github.com/kingsollyu/AppEnv-Kotlin) 模块相似，暂未开源\n\nSimilar to [AppEnv](https://github.com/kingsollyu/AppEnv-Kotlin) module, not open source yet.\n\n为你选择的应用程序传递你伪造的手机信息\n\nDeliver the fake informations you made about your phone to the apps you selected\n\n\n## Usage\n原作者并没有解释用法，以下的使用教程取自应用变量模块的描述：\n\n首先，你需要选择你想要传递手机伪装信息给哪些APP，\n\n(不仅仅在模块中选取，还需要添加到模块作用域中以确保模块可以作用于APP)\n\n然后在模块里填写手机的伪装信息，最后，只需单独重启这些APP即可.\n\nSince the author didn't explain the usage, the tutorial below is taken from the AppEnv module's description:\n\nFirst, you need to select the application which you want to deliver the fake informations to.\n\n(not only select it in the module app, but also select it in the Module Activation Scope page to make sure the module can take effect on the app)\n\nThen fill in the fake informations about your phone in the module app. Finally REBOOT THE SELECTED APPACATION ONLY.\nThat means you don't need to reboot your phone, only need to restart the app and enjoy it!\n\nNotice: \n\n - Based on xposed.Display in Simplified Chinese.\n\n\n\n## Stargazers over time\n\n[![Stargazers over time](https://starchart.cc/Xposed-Modules-Repo/com.variable.apkhook.svg)](https://starchart.cc/Xposed-Modules-Repo/com.variable.apkhook)","summary":"为你选择的应用程序传递你伪造的手机信息\nDeliver the fake informations you made about your phone to the apps you selected","sourceUrl":null,"hide":false,"additionalAuthors":null,"childGitHubReadme":{"childMarkdownRemark":{"excerpt":"com.variable.apkhook \n Module name 应用伪装 Author 酷安@暢越神密枫 QQ交流群：742185295 Description 功能与 应用变量 模块相似，暂未开源 Similar to AppEnv module, not open source yet. 为你选择的应用程序传递你伪造的手机信息 Deliver the fake informations you made about your phone to the apps you selecte…"}}}}],"pageInfo":{"currentPage":2,"pageCount":3}}},"pageContext":{"skip":30,"limit":30}},"staticQueryHashes":["418498416","63159454"]}